neuralk/VERSION.txt
neuralk/__init__.py
neuralk/_api.py
neuralk/_base_classifier.py
neuralk/_classifier.py
neuralk/cli.py
neuralk/datasets/__init__.py
neuralk/datasets/data/best_buy.parquet
neuralk/datasets/data/best_buy_test.parquet
neuralk/datasets/data/best_buy_test_small.parquet
neuralk/datasets/data/best_buy_train.parquet
neuralk/datasets/data/best_buy_train_small.parquet
neuralk/datasets/data/moons.csv
neuralk/exceptions.py
neuralk/neuralk.py
neuralk/utils/__init__.py
neuralk/utils/_remote_utils.py
neuralk/utils/docs.py
neuralk-0.1.0.dist-info/METADATA
neuralk-0.1.0.dist-info/WHEEL
neuralk-0.1.0.dist-info/entry_points.txt
neuralk-0.1.0.dist-info/licenses/LICENCE
neuralk-0.1.0.dist-info/RECORD
