Metadata-Version: 2.4
Name: neuralk
Version: 0.1.0
Summary: Neuralk SDK for Python
License-File: LICENCE
Author: Neuralk
Author-email: info@neuralk.com
Requires-Python: >=3.11,<4.0
Classifier: Programming Language :: Python :: 3
Classifier: Programming Language :: Python :: 3.11
Classifier: Programming Language :: Python :: 3.12
Classifier: Programming Language :: Python :: 3.13
Classifier: Programming Language :: Python :: 3.14
Requires-Dist: click (>=8.0.0)
Requires-Dist: cloudpickle (>=3.0.0)
Requires-Dist: httpx[http2] (>=0.25.2)
Requires-Dist: polars (>=1.11.0)
Requires-Dist: requests (>=2.32.3)
Requires-Dist: rich (>=13.0.0)
Requires-Dist: scikit-learn (>=1.4.2)
Requires-Dist: zstandard (>=0.22.0)
